botrun_langgraph_agents.py
botrun_langgraph_agents-4.7.241.dist-info/METADATA
botrun_langgraph_agents-4.7.241.dist-info/WHEEL
botrun_langgraph_agents-4.7.241.dist-info/entry_points.txt
botrun_langgraph_agents-4.7.241.dist-info/RECORD
