Metadata-Version: 2.3
Name: botrun_langgraph_agents
Version: 4.7.241
Requires-Dist: botrun-google-docs-reader
Requires-Dist: langchain
Requires-Dist: langchain-community
Requires-Dist: langchain-openai
Requires-Dist: langgraph
Requires-Dist: litellm
Requires-Dist: python-dotenv
Requires-Dist: tavily-python
